Kqlmagic/__init__.py
Kqlmagic/_debug_utils.py
Kqlmagic/_meta.py
Kqlmagic/_require.py
Kqlmagic/_test.py
Kqlmagic/_version.py
Kqlmagic/aad_helper.py
Kqlmagic/activate_kernel_command.py
Kqlmagic/adal_token_cache.py
Kqlmagic/ai_engine.py
Kqlmagic/aimon_engine.py
Kqlmagic/allow_py_comments_before_cell.py
Kqlmagic/allow_single_line_cell.py
Kqlmagic/aria_engine.py
Kqlmagic/bug_report.py
Kqlmagic/cache_client.py
Kqlmagic/cache_engine.py
Kqlmagic/column_guesser.py
Kqlmagic/commands_table.py
Kqlmagic/connection.py
Kqlmagic/constants.py
Kqlmagic/database_html.py
Kqlmagic/dependencies.py
Kqlmagic/dict_db_storage.py
Kqlmagic/display.py
Kqlmagic/dpapi_crypto.py
Kqlmagic/dpapi_crypto_msal.py
Kqlmagic/draft_client.py
Kqlmagic/email_notification.py
Kqlmagic/engine.py
Kqlmagic/exceptions.py
Kqlmagic/fernet_crypto.py
Kqlmagic/help.py
Kqlmagic/help_html.py
Kqlmagic/http_client.py
Kqlmagic/ipython_api.py
Kqlmagic/kql_client.py
Kqlmagic/kql_engine.py
Kqlmagic/kql_magic.py
Kqlmagic/kql_magic_core.py
Kqlmagic/kql_proxy.py
Kqlmagic/kql_response.py
Kqlmagic/kusto_client.py
Kqlmagic/kusto_engine.py
Kqlmagic/la_engine.py
Kqlmagic/log.py
Kqlmagic/magic_extension.py
Kqlmagic/msal_token_cache.py
Kqlmagic/my_aad_helper.py
Kqlmagic/my_aad_helper_msal.py
Kqlmagic/my_files_server.py
Kqlmagic/my_files_server_management.py
Kqlmagic/my_utils.py
Kqlmagic/os_dependent_api.py
Kqlmagic/palette.py
Kqlmagic/parameterizer.py
Kqlmagic/parser.py
Kqlmagic/python_command.py
Kqlmagic/results.py
Kqlmagic/sso_storage.py
Kqlmagic/version.py
KqlmagicCustom-0.1.114.post26.dist-info/LICENSE.TXT
KqlmagicCustom-0.1.114.post26.dist-info/METADATA
KqlmagicCustom-0.1.114.post26.dist-info/NOTICE.TXT
KqlmagicCustom-0.1.114.post26.dist-info/WHEEL
KqlmagicCustom-0.1.114.post26.dist-info/top_level.txt
KqlmagicCustom-0.1.114.post26.dist-info/RECORD
